deepsearcheath/__init__.py
deepsearcheath/deepsearch.py
deepsearcheath/api/__init__.py
deepsearcheath/api/client.py
deepsearcheath/compat/__init__.py
deepsearcheath/compat/legacy/__init__.py
deepsearcheath/compat/legacy/deepsearch.py
deepsearcheath/compat/legacy/local.py
deepsearcheath/data_provider/__init__.py
deepsearcheath/data_provider/constants.py
deepsearcheath/data_provider/market.py
deepsearcheath/data_provider/news.py
deepsearcheath/data_provider/store.py
deepsearcheath/data_provider/universe.py
deepsearcheath-3.0.5.dist-info/LICENSE
deepsearcheath-3.0.5.dist-info/METADATA
deepsearcheath-3.0.5.dist-info/WHEEL
deepsearcheath-3.0.5.dist-info/top_level.txt
deepsearcheath-3.0.5.dist-info/RECORD
