Metadata-Version: 2.1
Name: deepsearcheath
Version: 3.0.5
Summary: Heath taylored DeepSearch api.
Home-page: https://github.com/htaehpeed/deepsearcheath
Author: Heath
Author-email: heath@deepsearch.com
Classifier: Programming Language :: Python :: 3
Classifier: License :: OSI Approved :: MIT License
Classifier: Operating System :: OS Independent
Requires-Python: >=3.9
License-File: LICENSE
Requires-Dist: requests
Requires-Dist: pandas
Requires-Dist: numpy
Requires-Dist: python-dotenv
Requires-Dist: finance-datareader
Requires-Dist: pandas-datareader
Requires-Dist: aiohttp
Requires-Dist: tqdm
Requires-Dist: pyarrow
